{"name":"gh-pages-theme","body":"# About\r\nThis is a Github pages theme based on Twitter Bootstrap for your Github projects\r\n# License\r\n\r\nA Twitter Bootstrap Theme for your GitHub projects\r\n\r\nCopyright (C) 2011 We Creative\r\n\r\nThis program is free software: you can redistribute it and/or modify\r\nit under the terms of the GNU General Public License as published by\r\nthe Free Software Foundation, either version 3 of the License, or\r\n(at your option) any later version.\r\n\r\nThis program is distributed in the hope that it will be useful,\r\nbut WITHOUT ANY WARRANTY; without even the implied warranty of\r\nMERCHANTABILITY or FITNESS FOR A PARTICULAR PURPOSE.  See the\r\nGNU General Public License for more details.\r\n\r\nYou should have received a copy of the GNU General Public License\r\nalong with this program.  If not, see <http://www.gnu.org/licenses/gpl.html>.","tagline":"Twitter Bootstrap Theme for Github Pages","google":" UA-27151744-2","note":"Don't delete this file! It's used internally to help with page regeneration."}